iot_inspector/__init__.py
iot_inspector/common.py
iot_inspector/dashboard.py
iot_inspector/device_detail_page.py
iot_inspector/device_list_page.py
iot_inspector/main.py
iot_inspector/overview_page.py
iot_inspector/page_manager.py
iot_inspector/settings_page.py
iot_inspector/sidebar.py
iot_inspector/.streamlit/config.toml
iot_inspector/analysis/__init__.py
iot_inspector/analysis/anonymize.py
iot_inspector/analysis/pcap_time_series.py
iot_inspector/background/__init__.py
iot_inspector/background/device_id_api_thread.py
iot_inspector/background/label_packet_thread.py
iot_inspector/data/activity.json
iot_inspector/data/settings.json
iot_inspector/server/README.md
iot_inspector/server/__init__.py
iot_inspector/server/directory_explore.py
iot_inspector/server/packet_collector.py
iot_inspector/server/pcap_check.py
iot_inspector/static/images/inspector-logo.png
iot_inspector-3.0.13.dist-info/licenses/LICENSE
iot_inspector-3.0.13.dist-info/METADATA
iot_inspector-3.0.13.dist-info/WHEEL
iot_inspector-3.0.13.dist-info/top_level.txt
iot_inspector-3.0.13.dist-info/RECORD
