Metadata-Version: 2.4
Name: iot-inspector
Version: 3.0.13
Summary: IoT Inspector Client for analyzing IoT device firmware
Author-email: Danny Huang <dhuang@nyu.edu>, Andrew Quijano <andrew.quijano@nyu.edu>
License-Expression: Apache-2.0
Project-URL: Homepage, https://inspector.engineering.nyu.edu/
Project-URL: Source, https://github.com/nyu-mlab/iot-inspector-client/
Project-URL: Tracker, https://github.com/nyu-mlab/iot-inspector-client/issues
Classifier: Programming Language :: Python :: 3
Classifier: Operating System :: OS Independent
Requires-Python: ==3.13.*
License-File: LICENSE
Requires-Dist: libinspector==1.0.12
Requires-Dist: streamlit>=1.52.1
Requires-Dist: matplotlib==3.10.8
Dynamic: license-file
